aliyunsdknas/__init__.py
aliyunsdknas/endpoint.py
aliyunsdknas/request/__init__.py
aliyunsdknas/request/v20170626/AddClientToBlackListRequest.py
aliyunsdknas/request/v20170626/ApplyAutoSnapshotPolicyRequest.py
aliyunsdknas/request/v20170626/ApplyDataFlowAutoRefreshRequest.py
aliyunsdknas/request/v20170626/AttachVscToFilesystemsRequest.py
aliyunsdknas/request/v20170626/CancelAutoSnapshotPolicyRequest.py
aliyunsdknas/request/v20170626/CancelDataFlowAutoRefreshRequest.py
aliyunsdknas/request/v20170626/CancelDataFlowSubTaskRequest.py
aliyunsdknas/request/v20170626/CancelDataFlowTaskRequest.py
aliyunsdknas/request/v20170626/CancelDirQuotaRequest.py
aliyunsdknas/request/v20170626/CancelFilesetQuotaRequest.py
aliyunsdknas/request/v20170626/CancelLifecycleRetrieveJobRequest.py
aliyunsdknas/request/v20170626/CancelRecycleBinJobRequest.py
aliyunsdknas/request/v20170626/ChangeResourceGroupRequest.py
aliyunsdknas/request/v20170626/CreateAccessGroupRequest.py
aliyunsdknas/request/v20170626/CreateAccessPointRequest.py
aliyunsdknas/request/v20170626/CreateAccessRuleRequest.py
aliyunsdknas/request/v20170626/CreateAutoSnapshotPolicyRequest.py
aliyunsdknas/request/v20170626/CreateDataFlowRequest.py
aliyunsdknas/request/v20170626/CreateDataFlowSubTaskRequest.py
aliyunsdknas/request/v20170626/CreateDataFlowTaskRequest.py
aliyunsdknas/request/v20170626/CreateDirRequest.py
aliyunsdknas/request/v20170626/CreateFileRequest.py
aliyunsdknas/request/v20170626/CreateFileSystemRequest.py
aliyunsdknas/request/v20170626/CreateFilesetRequest.py
aliyunsdknas/request/v20170626/CreateLDAPConfigRequest.py
aliyunsdknas/request/v20170626/CreateLifecyclePolicyRequest.py
aliyunsdknas/request/v20170626/CreateLifecycleRetrieveJobRequest.py
aliyunsdknas/request/v20170626/CreateLogAnalysisRequest.py
aliyunsdknas/request/v20170626/CreateMountTargetRequest.py
aliyunsdknas/request/v20170626/CreateProtocolMountTargetRequest.py
aliyunsdknas/request/v20170626/CreateProtocolServiceRequest.py
aliyun_python_sdk_nas-3.14.5.dist-info/LICENSE
aliyun_python_sdk_nas-3.14.5.dist-info/METADATA
aliyun_python_sdk_nas-3.14.5.dist-info/WHEEL
aliyun_python_sdk_nas-3.14.5.dist-info/top_level.txt
aliyun_python_sdk_nas-3.14.5.dist-info/RECORD
